LICENSE
README.md
setup.py
selenextra/__init__.py
selenextra/exceptions.py
selenextra.egg-info/PKG-INFO
selenextra.egg-info/SOURCES.txt
selenextra.egg-info/dependency_links.txt
selenextra.egg-info/requires.txt
selenextra.egg-info/top_level.txt