Metadata-Version: 2.1
Name: selenextra
Version: 1.0.5
Summary: Bringing additional features to Selenium
Home-page: https://github.com/nguyenvantat1182002/SeleneXtra
Author: Tat Nguyen Van
Author-email: nguyenvantat1182002@gmail.com
Classifier: Development Status :: 3 - Alpha
Classifier: License :: OSI Approved :: GNU General Public License v3 (GPLv3)
Classifier: Programming Language :: Python :: 3.8
Classifier: Programming Language :: Python :: 3.9
Classifier: Programming Language :: Python :: 3.10
License-File: LICENSE
